{
"ons":{
"time": {
"index":["spdx",  "official"]
},
"concept":{
"label":["population", "% of population"],
"units":["count", "%"],
"max":[        1871,         0.96]
},
"sums":{
"series1":[       94616,        94052],
"series2":[      100114,        99533]
},
"dimension":{
"label":"age",
"index":["0","1","2","3","4","5","6","7","8","9","10","11","12","13","14","15","16","17","18","19","20","21","22","23","24","25","26","27","28","29","30","31","32","33","34","35","36","37","38","39","40","41","42","43","44","45","46","47","48","49","50","51","52","53","54","55","56","57","58","59","60","61","62","63","64","65","66","67","68","69","70","71","72","73","74","75","76","77","78","79","80","81","82","83","84","85","86","87","88","89","90+"]
},
"series":["male", "female"],
"value":[[[[        1303,         0.67], [        1385,         0.72]],
[[        1355,          0.7], [        1429,         0.74]],
[[        1372,          0.7], [        1519,         0.78]],
[[        1490,         0.77], [        1501,         0.78]],
[[        1498,         0.77], [        1533,         0.79]],
[[        1525,         0.78], [        1487,         0.77]],
[[        1521,         0.78], [        1374,         0.71]],
[[        1350,         0.69], [        1348,          0.7]],
[[        1343,         0.69], [        1239,         0.64]],
[[        1263,         0.65], [        1199,         0.62]],
[[        1181,         0.61], [        1118,         0.58]],
[[        1127,         0.58], [        1118,         0.58]],
[[        1135,         0.58], [        1036,         0.54]],
[[        1046,         0.54], [         992,         0.51]],
[[         980,          0.5], [         972,          0.5]],
[[         975,          0.5], [        1053,         0.54]],
[[        1044,         0.54], [        1006,         0.52]],
[[        1029,         0.53], [         892,         0.46]],
[[         894,         0.46], [         989,         0.51]],
[[         790,         0.41], [         767,          0.4]],
[[         666,         0.34], [         727,         0.38]],
[[         793,         0.41], [         660,         0.34]],
[[         733,         0.38], [         748,         0.39]],
[[         836,         0.43], [         867,         0.45]],
[[         916,         0.47], [         819,         0.42]],
[[         836,         0.43], [         996,         0.51]],
[[         984,         0.51], [        1091,         0.56]],
[[        1159,          0.6], [        1015,         0.52]],
[[        1016,         0.52], [        1122,         0.58]],
[[        1111,         0.57], [        1235,         0.64]],
[[        1266,         0.65], [        1260,         0.65]],
[[        1292,         0.66], [        1427,         0.74]],
[[        1521,         0.78], [        1562,         0.81]],
[[        1532,         0.79], [        1499,         0.77]],
[[        1499,         0.77], [        1572,         0.81]],
[[        1553,          0.8], [        1673,         0.86]],
[[        1653,         0.85], [        1760,         0.91]],
[[        1748,          0.9], [        1730,         0.89]],
[[        1738,         0.89], [        1697,         0.88]],
[[        1708,         0.88], [        1799,         0.93]],
[[        1785,         0.92], [        1682,         0.87]],
[[        1692,         0.87], [        1785,         0.92]],
[[        1740,         0.89], [        1745,          0.9]],
[[        1752,          0.9], [        1673,         0.86]],
[[        1666,         0.86], [        1491,         0.77]],
[[        1482,         0.76], [        1590,         0.82]],
[[        1555,          0.8], [        1537,         0.79]],
[[        1531,         0.79], [        1478,         0.76]],
[[        1473,         0.76], [        1536,         0.79]],
[[        1531,         0.79], [        1480,         0.76]],
[[        1482,         0.76], [        1448,         0.75]],
[[        1453,         0.75], [        1354,          0.7]],
[[        1349,         0.69], [        1354,          0.7]],
[[        1354,          0.7], [        1189,         0.61]],
[[        1194,         0.61], [        1199,         0.62]],
[[        1169,          0.6], [        1109,         0.57]],
[[        1119,         0.57], [        1107,         0.57]],
[[        1094,         0.56], [        1103,         0.57]],
[[        1079,         0.55], [        1040,         0.54]],
[[        1027,         0.53], [         973,          0.5]],
[[         957,         0.49], [         929,         0.48]],
[[         918,         0.47], [         870,         0.45]],
[[         858,         0.44], [         905,         0.47]],
[[         888,         0.46], [         933,         0.48]],
[[         922,         0.47], [         908,         0.47]],
[[         906,         0.47], [         902,         0.47]],
[[         887,         0.46], [         953,         0.49]],
[[         931,         0.48], [        1015,         0.52]],
[[         987,         0.51], [         824,         0.43]],
[[         811,         0.42], [         730,         0.38]],
[[         717,         0.37], [         774,          0.4]],
[[         750,         0.39], [         598,         0.31]],
[[         591,          0.3], [         542,         0.28]],
[[         524,         0.27], [         519,         0.27]],
[[         501,         0.26], [         505,         0.26]],
[[         485,         0.25], [         502,         0.26]],
[[         494,         0.25], [         472,         0.24]],
[[         467,         0.24], [         383,          0.2]],
[[         372,         0.19], [         422,         0.22]],
[[         398,          0.2], [         357,         0.18]],
[[         326,         0.17], [         341,         0.18]],
[[         324,         0.17], [         325,         0.17]],
[[         304,         0.16], [         310,         0.16]],
[[         285,         0.15], [         312,         0.16]],
[[         292,         0.15], [         263,         0.14]],
[[         239,         0.12], [         224,         0.12]],
[[         203,          0.1], [         184,          0.1]],
[[         164,         0.08], [         188,          0.1]],
[[         166,         0.09], [         174,         0.09]],
[[         145,         0.07], [         131,         0.07]],
[[         496,         0.25], [         468,         0.24]]],
[[[        1289,         0.66], [        1329,         0.69]],
[[        1305,         0.67], [        1411,         0.73]],
[[        1403,         0.72], [        1444,         0.75]],
[[        1447,         0.74], [        1417,         0.73]],
[[        1413,         0.73], [        1465,         0.76]],
[[        1466,         0.75], [        1358,          0.7]],
[[        1350,         0.69], [        1402,         0.72]],
[[        1408,         0.72], [        1261,         0.65]],
[[        1236,         0.63], [        1217,         0.63]],
[[        1216,         0.62], [        1147,         0.59]],
[[        1167,          0.6], [        1077,         0.56]],
[[        1074,         0.55], [        1126,         0.58]],
[[        1132,         0.58], [         952,         0.49]],
[[         936,         0.48], [        1000,         0.52]],
[[        1007,         0.52], [        1038,         0.54]],
[[        1045,         0.54], [        1017,         0.53]],
[[        1025,         0.53], [         962,          0.5]],
[[         963,         0.49], [         881,         0.46]],
[[         856,         0.44], [         879,         0.45]],
[[         799,         0.41], [         777,          0.4]],
[[         724,         0.37], [         742,         0.38]],
[[         788,          0.4], [         848,         0.44]],
[[         924,         0.47], [         919,         0.47]],
[[         981,          0.5], [         964,          0.5]],
[[        1041,         0.53], [         960,          0.5]],
[[         971,          0.5], [        1019,         0.53]],
[[        1063,         0.55], [        1142,         0.59]],
[[        1155,         0.59], [        1158,          0.6]],
[[        1193,         0.61], [        1145,         0.59]],
[[        1166,          0.6], [        1279,         0.66]],
[[        1303,         0.67], [        1496,         0.77]],
[[        1476,         0.76], [        1557,          0.8]],
[[        1581,         0.81], [        1679,         0.87]],
[[        1704,         0.88], [        1732,         0.89]],
[[        1707,         0.88], [        1862,         0.96]],
[[        1871,         0.96], [        1790,         0.92]],
[[        1797,         0.92], [        1774,         0.92]],
[[        1750,          0.9], [        1710,         0.88]],
[[        1696,         0.87], [        1677,         0.87]],
[[        1647,         0.85], [        1784,         0.92]],
[[        1761,          0.9], [        1804,         0.93]],
[[        1804,         0.93], [        1767,         0.91]],
[[        1763,         0.91], [        1744,          0.9]],
[[        1738,         0.89], [        1689,         0.87]],
[[        1699,         0.87], [        1598,         0.83]],
[[        1602,         0.82], [        1585,         0.82]],
[[        1564,          0.8], [        1547,          0.8]],
[[        1534,         0.79], [        1618,         0.84]],
[[        1620,         0.83], [        1480,         0.76]],
[[        1483,         0.76], [        1488,         0.77]],
[[        1483,         0.76], [        1478,         0.76]],
[[        1458,         0.75], [        1406,         0.73]],
[[        1401,         0.72], [        1339,         0.69]],
[[        1321,         0.68], [        1323,         0.68]],
[[        1330,         0.68], [        1178,         0.61]],
[[        1166,          0.6], [        1128,         0.58]],
[[        1139,         0.58], [        1115,         0.58]],
[[        1120,         0.58], [        1139,         0.59]],
[[        1114,         0.57], [         995,         0.51]],
[[         991,         0.51], [        1032,         0.53]],
[[        1006,         0.52], [         995,         0.51]],
[[         988,         0.51], [         959,          0.5]],
[[         937,         0.48], [         970,          0.5]],
[[         971,          0.5], [         961,          0.5]],
[[         961,         0.49], [         918,         0.47]],
[[         903,         0.46], [        1004,         0.52]],
[[         999,         0.51], [        1065,         0.55]],
[[        1035,         0.53], [        1109,         0.57]],
[[        1091,         0.56], [         822,         0.42]],
[[         819,         0.42], [         783,          0.4]],
[[         764,         0.39], [         848,         0.44]],
[[         842,         0.43], [         703,         0.36]],
[[         703,         0.36], [         644,         0.33]],
[[         624,         0.32], [         567,         0.29]],
[[         551,         0.28], [         611,         0.32]],
[[         603,         0.31], [         634,         0.33]],
[[         621,         0.32], [         554,         0.29]],
[[         543,         0.28], [         476,         0.25]],
[[         465,         0.24], [         529,         0.27]],
[[         514,         0.26], [         501,         0.26]],
[[         481,         0.25], [         438,         0.23]],
[[         411,         0.21], [         412,         0.21]],
[[         391,          0.2], [         473,         0.24]],
[[         448,         0.23], [         402,         0.21]],
[[         371,         0.19], [         444,         0.23]],
[[         415,         0.21], [         342,         0.18]],
[[         320,         0.16], [         355,         0.18]],
[[         335,         0.17], [         326,         0.17]],
[[         299,         0.15], [         282,         0.15]],
[[         254,         0.13], [         301,         0.16]],
[[        1283,         0.66], [        1255,         0.65]]]]}}
